{"v":"5.12.1","fr":30,"ip":0,"op":60,"w":1500,"h":1500,"nm":"Notification","ddd":0,"assets":[],"layers":[{"ddd":0,"ind":1,"ty":4,"nm":"Notification","sr":1,"ks":{"o":{"a":0,"k":100,"ix":11},"r":{"a":1,"k":[{"i":{"x":[0.667],"y":[1]},"o":{"x":[0.333],"y":[0]},"t":16,"s":[0]},{"i":{"x":[0.667],"y":[1]},"o":{"x":[0.333],"y":[0]},"t":21,"s":[-10]},{"i":{"x":[0.667],"y":[1]},"o":{"x":[0.333],"y":[0]},"t":26,"s":[10]},{"i":{"x":[0.667],"y":[1]},"o":{"x":[0.333],"y":[0]},"t":31,"s":[-10]},{"i":{"x":[0.667],"y":[1]},"o":{"x":[0.333],"y":[0]},"t":36,"s":[10]},{"t":41,"s":[0]}],"ix":10},"p":{"a":0,"k":[751.606,439.162,0],"ix":2,"l":2},"a":{"a":0,"k":[377.392,50.312,0],"ix":1,"l":2},"s":{"a":0,"k":[180,180,100],"ix":6,"l":2}},"ao":0,"shapes":[{"ty":"gr","it":[{"ind":0,"ty":"sh","ix":1,"ks":{"a":0,"k":{"i":[[0,40.674],[40.674,0],[0,-40.674],[-40.674,0]],"o":[[0,-40.674],[-40.674,0],[0,40.674],[40.674,0]],"v":[[73.647,0],[0,-73.647],[-73.647,0],[0,73.647]],"c":true},"ix":2},"nm":"Path 1","mn":"ADBE Vector Shape - Group","hd":false},{"ty":"fl","c":{"a":0,"k":[1,0.654901960784,0.20000001496,1],"ix":4},"o":{"a":0,"k":100,"ix":5},"r":1,"bm":0,"nm":"Fill 1","mn":"ADBE Vector Graphic - Fill","hd":false},{"ty":"tr","p":{"a":0,"k":[478.154,77.895],"ix":2},"a":{"a":0,"k":[0,0],"ix":1},"s":{"a":1,"k":[{"i":{"x":[0,0],"y":[1,1]},"o":{"x":[0.333,0.333],"y":[0,0]},"t":12,"s":[0,0]},{"i":{"x":[0.535,0.535],"y":[1,1]},"o":{"x":[0.536,0.536],"y":[0,0]},"t":22,"s":[120,120]},{"i":{"x":[0.667,0.667],"y":[1,1]},"o":{"x":[0.333,0.333],"y":[0,0]},"t":30,"s":[90,90]},{"i":{"x":[0.03,0.03],"y":[1,1]},"o":{"x":[0.167,0.167],"y":[0,0]},"t":35,"s":[100,100]},{"i":{"x":[0,0],"y":[1,1]},"o":{"x":[0.333,0.333],"y":[0,0]},"t":46,"s":[100,100]},{"i":{"x":[0,0],"y":[1,1]},"o":{"x":[0.333,0.333],"y":[0,0]},"t":54,"s":[110,110]},{"t":58,"s":[0,0]}],"ix":3},"r":{"a":0,"k":0,"ix":6},"o":{"a":0,"k":100,"ix":7},"sk":{"a":0,"k":0,"ix":4},"sa":{"a":0,"k":0,"ix":5},"nm":"Transform"}],"nm":"Notification","np":2,"cix":2,"bm":0,"ix":1,"mn":"ADBE Vector Group","hd":false},{"ty":"gr","it":[{"ind":0,"ty":"sh","ix":1,"ks":{"a":1,"k":[{"i":{"x":0,"y":1},"o":{"x":0.333,"y":0},"t":0,"s":[{"i":[[-1.628,25.681],[0.056,3.912],[70.765,0.302],[0,-77.512],[-0.174,-2.932],[9.039,-24.612],[0,0],[-20.456,0],[0,0],[7.4,20.152],[0,0]],"o":[[0.243,-3.833],[-1.072,-74.772],[-73.419,-0.312],[0,2.979],[1.565,26.349],[0,0],[-7.401,20.153],[0,0],[20.456,0],[0,0],[-8.812,-23.994]],"v":[[132.184,9.618],[132.468,-2.003],[0.545,-139.843],[-132.482,0.156],[-132.221,9.024],[-143.954,86.358],[-148.335,98.285],[-121.211,140.156],[121.21,140.156],[148.335,98.287],[143.463,85.019]],"c":true}]},{"i":{"x":0.667,"y":1},"o":{"x":0.333,"y":0},"t":20,"s":[{"i":[[-1.628,25.681],[-0.131,3.91],[70.765,0.302],[-3.697,-85.922],[-0.174,-2.932],[9.039,-24.612],[0,0],[-44.46,7.326],[-27.252,-2.489],[1.873,24.28],[0,0]],"o":[[0.243,-3.833],[2.74,-81.819],[-73.419,-0.312],[0.128,2.976],[1.565,26.349],[0,0],[-7.012,26.503],[78.086,-12.867],[65.943,6.022],[0,0],[-8.812,-23.994]],"v":[[132.185,9.618],[132.469,-2.003],[0.545,-149.288],[-132.482,0.156],[-132.221,9.024],[-143.676,75.246],[-148.057,87.174],[-105.377,86.822],[90.377,85.156],[148.891,89.398],[143.464,76.131]],"c":true}]},{"i":{"x":0.264,"y":1},"o":{"x":0.619,"y":0},"t":40,"s":[{"i":[[-1.628,25.681],[-0.131,3.91],[70.765,0.302],[-3.697,-85.922],[-0.174,-2.932],[9.039,-24.612],[0,0],[-44.46,7.326],[-27.252,-2.489],[1.873,24.28],[0,0]],"o":[[0.243,-3.833],[2.74,-81.819],[-73.419,-0.312],[0.128,2.976],[1.565,26.349],[0,0],[-7.012,26.503],[78.086,-12.866],[65.943,6.022],[0,0],[-8.812,-23.994]],"v":[[132.185,9.618],[132.469,-2.003],[0.545,-149.288],[-132.482,0.156],[-132.221,9.024],[-143.676,75.246],[-148.057,87.174],[-105.377,86.822],[90.377,85.156],[148.891,89.398],[143.464,76.131]],"c":true}]},{"t":59,"s":[{"i":[[-1.628,25.681],[0.056,3.912],[70.765,0.302],[0,-77.512],[-0.174,-2.932],[9.039,-24.612],[0,0],[-20.456,0],[0,0],[7.4,20.152],[0,0]],"o":[[0.243,-3.833],[-1.072,-74.772],[-73.419,-0.312],[0,2.979],[1.565,26.349],[0,0],[-7.401,20.153],[0,0],[20.456,0],[0,0],[-8.812,-23.994]],"v":[[132.185,9.618],[132.469,-2.003],[0.546,-139.843],[-132.482,0.156],[-132.221,9.024],[-143.954,86.358],[-148.335,98.285],[-121.211,140.156],[121.211,140.156],[148.336,98.287],[143.464,85.019]],"c":true}]}],"ix":2},"nm":"Path 1","mn":"ADBE Vector Shape - Group","hd":false},{"ty":"st","c":{"a":0,"k":[0.207843152214,0.125490196078,0.023529413635,1],"ix":3},"o":{"a":0,"k":100,"ix":4},"w":{"a":0,"k":20,"ix":5},"lc":2,"lj":2,"bm":0,"nm":"Stroke 1","mn":"ADBE Vector Graphic - Stroke","hd":false},{"ty":"fl","c":{"a":0,"k":[1,1,1,1],"ix":4},"o":{"a":0,"k":100,"ix":5},"r":1,"bm":0,"nm":"Fill 1","mn":"ADBE Vector Graphic - Fill","hd":false},{"ty":"tr","p":{"a":0,"k":[376.847,190.155],"ix":2},"a":{"a":0,"k":[0,0],"ix":1},"s":{"a":0,"k":[100,100],"ix":3},"r":{"a":0,"k":0,"ix":6},"o":{"a":0,"k":100,"ix":7},"sk":{"a":0,"k":0,"ix":4},"sa":{"a":0,"k":0,"ix":5},"nm":"Transform"}],"nm":"bell 1 bottom","np":3,"cix":2,"bm":0,"ix":2,"mn":"ADBE Vector Group","hd":false},{"ty":"gr","it":[{"ind":0,"ty":"sh","ix":1,"ks":{"a":0,"k":{"i":[[0,35.942],[35.941,0],[0,-35.942],[-35.942,0]],"o":[[0,-35.942],[-35.942,0],[0,35.942],[35.941,0]],"v":[[65.078,0],[0,-65.078],[-65.078,0],[0,65.078]],"c":true},"ix":2},"nm":"Path 1","mn":"ADBE Vector Shape - Group","hd":false},{"ty":"st","c":{"a":0,"k":[0.207843152214,0.125490196078,0.023529413635,1],"ix":3},"o":{"a":0,"k":100,"ix":4},"w":{"a":0,"k":20,"ix":5},"lc":2,"lj":2,"bm":0,"nm":"Stroke 1","mn":"ADBE Vector Graphic - Stroke","hd":false},{"ty":"fl","c":{"a":0,"k":[1,1,1,1],"ix":4},"o":{"a":0,"k":100,"ix":5},"r":1,"bm":0,"nm":"Fill 1","mn":"ADBE Vector Graphic - Fill","hd":false},{"ty":"tr","p":{"a":1,"k":[{"i":{"x":0,"y":1},"o":{"x":0.333,"y":0},"t":0,"s":[376.847,267.811],"to":[0,-2.914],"ti":[0,3.402]},{"i":{"x":0.667,"y":1},"o":{"x":0.333,"y":0},"t":20,"s":[374.625,249.753],"to":[0,-0.101],"ti":[0,3.402]},{"i":{"x":0.264,"y":1},"o":{"x":0.619,"y":0},"t":40,"s":[374.625,249.753],"to":[0,-0.101],"ti":[0,3]},{"t":59,"s":[376.847,267.811]}],"ix":2},"a":{"a":0,"k":[-2.222,-63.333],"ix":1},"s":{"a":0,"k":[100,100],"ix":3},"r":{"a":1,"k":[{"i":{"x":[0.833],"y":[1]},"o":{"x":[0.167],"y":[0]},"t":17,"s":[0]},{"i":{"x":[0.833],"y":[1]},"o":{"x":[0.167],"y":[0]},"t":22,"s":[-33]},{"i":{"x":[0.833],"y":[1]},"o":{"x":[0.167],"y":[0]},"t":27,"s":[33]},{"i":{"x":[0.833],"y":[1]},"o":{"x":[0.167],"y":[0]},"t":32,"s":[-33]},{"i":{"x":[0.667],"y":[1]},"o":{"x":[0.167],"y":[0]},"t":37,"s":[33]},{"i":{"x":[0.667],"y":[1]},"o":{"x":[0.333],"y":[0]},"t":42,"s":[-20]},{"t":46,"s":[0]}],"ix":6},"o":{"a":0,"k":100,"ix":7},"sk":{"a":0,"k":0,"ix":4},"sa":{"a":0,"k":0,"ix":5},"nm":"Transform"}],"nm":"circle","np":3,"cix":2,"bm":0,"ix":3,"mn":"ADBE Vector Group","hd":false},{"ty":"gr","it":[{"ind":0,"ty":"sh","ix":1,"ks":{"a":1,"k":[{"i":{"x":0,"y":1},"o":{"x":0.333,"y":0},"t":0,"s":[{"i":[[-1.628,25.681],[0.056,3.912],[70.765,0.302],[0,-77.512],[-0.174,-2.932],[9.039,-24.612],[0,0],[-20.456,0],[0,0],[7.4,20.152],[0,0]],"o":[[0.243,-3.833],[-1.072,-74.772],[-73.419,-0.312],[0,2.979],[1.565,26.349],[0,0],[-7.401,20.153],[0,0],[20.456,0],[0,0],[-8.812,-23.994]],"v":[[132.184,9.618],[132.468,-2.003],[0.545,-139.843],[-132.482,0.156],[-132.221,9.024],[-143.954,86.358],[-148.335,98.285],[-121.211,140.156],[121.21,140.156],[148.335,98.287],[143.463,85.019]],"c":true}]},{"i":{"x":0.667,"y":1},"o":{"x":0.333,"y":0},"t":20,"s":[{"i":[[-1.628,25.681],[-0.131,3.91],[70.765,0.302],[-3.697,-85.922],[-0.174,-2.932],[9.039,-24.612],[0,0],[-25.74,-10.649],[-24.109,12.946],[3.818,17.614],[0,0]],"o":[[0.243,-3.833],[2.74,-81.819],[-73.419,-0.312],[0.128,2.976],[1.565,26.349],[0,0],[-7.401,20.153],[81.697,33.8],[23.443,-12.589],[0,0],[-8.812,-23.994]],"v":[[132.184,9.618],[132.468,-2.003],[0.545,-149.288],[-132.482,0.156],[-132.221,9.024],[-143.676,75.246],[-148.057,87.174],[-121.211,131.267],[120.933,130.711],[148.891,89.398],[143.463,76.131]],"c":true}]},{"i":{"x":0.264,"y":1},"o":{"x":0.619,"y":0},"t":40,"s":[{"i":[[-1.628,25.681],[-0.131,3.91],[70.765,0.302],[-3.697,-85.922],[-0.174,-2.932],[9.039,-24.612],[0,0],[-25.74,-10.649],[-24.109,12.946],[3.818,17.614],[0,0]],"o":[[0.243,-3.833],[2.74,-81.819],[-73.419,-0.312],[0.128,2.976],[1.565,26.349],[0,0],[-7.401,20.153],[81.697,33.8],[23.443,-12.589],[0,0],[-8.812,-23.994]],"v":[[132.184,9.618],[132.468,-2.003],[0.545,-149.288],[-132.482,0.156],[-132.221,9.024],[-143.676,75.246],[-148.057,87.174],[-121.211,131.267],[120.933,130.711],[148.891,89.398],[143.463,76.131]],"c":true}]},{"t":59,"s":[{"i":[[-1.628,25.681],[0.056,3.912],[70.765,0.302],[0,-77.512],[-0.174,-2.932],[9.039,-24.612],[0,0],[-20.456,0],[0,0],[7.4,20.152],[0,0]],"o":[[0.243,-3.833],[-1.072,-74.772],[-73.419,-0.312],[0,2.979],[1.565,26.349],[0,0],[-7.401,20.153],[0,0],[20.456,0],[0,0],[-8.812,-23.994]],"v":[[132.185,9.618],[132.469,-2.003],[0.546,-139.843],[-132.482,0.156],[-132.221,9.024],[-143.954,86.358],[-148.335,98.285],[-121.211,140.156],[121.211,140.156],[148.336,98.287],[143.464,85.019]],"c":true}]}],"ix":2},"nm":"Path 1","mn":"ADBE Vector Shape - Group","hd":false},{"ty":"st","c":{"a":0,"k":[0.207843152214,0.125490196078,0.023529413635,1],"ix":3},"o":{"a":0,"k":100,"ix":4},"w":{"a":0,"k":20,"ix":5},"lc":2,"lj":2,"bm":0,"nm":"Stroke 1","mn":"ADBE Vector Graphic - Stroke","hd":false},{"ty":"fl","c":{"a":0,"k":[1,1,1,1],"ix":4},"o":{"a":0,"k":100,"ix":5},"r":1,"bm":0,"nm":"Fill 1","mn":"ADBE Vector Graphic - Fill","hd":false},{"ty":"tr","p":{"a":0,"k":[376.847,190.155],"ix":2},"a":{"a":0,"k":[0,0],"ix":1},"s":{"a":0,"k":[100,100],"ix":3},"r":{"a":0,"k":0,"ix":6},"o":{"a":0,"k":100,"ix":7},"sk":{"a":0,"k":0,"ix":4},"sa":{"a":0,"k":0,"ix":5},"nm":"Transform"}],"nm":"bell 1","np":3,"cix":2,"bm":0,"ix":4,"mn":"ADBE Vector Group","hd":false}],"ip":0,"op":60,"st":0,"ct":1,"bm":0}],"markers":[],"props":{}}